douyin_wenan_mcp_server/__init__.py
douyin_wenan_mcp_server/server.py
douyin_wenan_mcp_server-0.1.0.dist-info/METADATA
douyin_wenan_mcp_server-0.1.0.dist-info/WHEEL
douyin_wenan_mcp_server-0.1.0.dist-info/entry_points.txt
douyin_wenan_mcp_server-0.1.0.dist-info/licenses/LICENSE
douyin_wenan_mcp_server-0.1.0.dist-info/RECORD
