Metadata-Version: 2.4
Name: douyin-wenan-mcp-server
Version: 0.1.0
Summary: MCP server for downloading Douyin videos and extracting text from audio
Project-URL: Homepage, https://github.com/yzfly/douyin-wenan-mcp-server
Project-URL: Repository, https://github.com/yzfly/douyin-wenan-mcp-server
Project-URL: Issues, https://github.com/yzfly/douyin-wenan-mcp-server/issues
Author-email: yzfly <yz.liu.me@gmail.com>
License: MIT
License-File: LICENSE
Classifier: Development Status :: 3 - Alpha
Classifier: Intended Audience :: Developers
Classifier: License :: OSI Approved :: MIT License
Classifier: Programming Language :: Python :: 3
Classifier: Programming Language :: Python :: 3.8
Classifier: Programming Language :: Python :: 3.9
Classifier: Programming Language :: Python :: 3.10
Classifier: Programming Language :: Python :: 3.11
Classifier: Programming Language :: Python :: 3.12
Requires-Python: >=3.8
Requires-Dist: ffmpeg-python
Requires-Dist: mcp>=1.0.0
Requires-Dist: requests
Requires-Dist: tqdm
